__init__.py
crypto.py
debug.py
decorators.py
dev.py
ecstore.py
extensions.py
filesys.py
flow.py
gitcli.py
initializer.py
logger.py
mockable.py
osbridge.py
parser.py
setup.py
shell.py
sqlitex.py
ssh.py
tools.py
tsv.py
utils.py
yamlex.py
helpers/__init__.py
helpers/filesys.py
laufire/__init__.py
laufire/crypto.py
laufire/debug.py
laufire/decorators.py
laufire/dev.py
laufire/ecstore.py
laufire/extensions.py
laufire/filesys.py
laufire/flow.py
laufire/gitcli.py
laufire/initializer.py
laufire/logger.py
laufire/mockable.py
laufire/osbridge.py
laufire/parser.py
laufire/setup.py
laufire/shell.py
laufire/sqlitex.py
laufire/ssh.py
laufire/tools.py
laufire/tsv.py
laufire/utils.py
laufire/yamlex.py
laufire/helpers/__init__.py
laufire/helpers/filesys.py
laufire/mock/__init__.py
laufire/mock/ssh.py
laufire/tools/__init__.py
laufire/tools/retry.py
laufire/tools/ss.py
laufire.egg-info/PKG-INFO
laufire.egg-info/SOURCES.txt
laufire.egg-info/dependency_links.txt
laufire.egg-info/requires.txt
laufire.egg-info/top_level.txt
laufire.egg-info/zip-safe
mock/__init__.py
mock/ssh.py
tools/__init__.py
tools/retry.py
tools/ss.py
laufire-0.0.3.dist-info/LICENSE.rst
laufire-0.0.3.dist-info/METADATA
laufire-0.0.3.dist-info/WHEEL
laufire-0.0.3.dist-info/top_level.txt
laufire-0.0.3.dist-info/zip-safe
laufire-0.0.3.dist-info/RECORD
