Metadata-Version: 2.1
Name: laufire
Version: 0.0.3
Summary: laufire - a set of utilities to help with automation
Home-page: UNKNOWN
Author: Laufire Technologies
License: MIT
Keywords: laufire utilities automation MIT
Platform: any
Classifier: Development Status :: 2 - Pre-Alpha
Classifier: Environment :: Console
Classifier: Intended Audience :: Developers
Classifier: Operating System :: OS Independent
Classifier: Natural Language :: English
Classifier: Programming Language :: Python :: 2.7
Classifier: Programming Language :: Python :: 3
Classifier: Programming Language :: Python :: 3.3
Classifier: Programming Language :: Python :: 3.4
Classifier: Topic :: Software Development
Classifier: Topic :: Utilities
Requires-Python: >=2.7.10
Requires-Dist: HiYaPyCo (>=0.4.0)
Requires-Dist: PyYAML (>=3.11)
Requires-Dist: colorama (>=0.3.3)
Requires-Dist: matplotlib (>=2.0.0b4)
Requires-Dist: paramiko (>=2.0.2)
Requires-Dist: pyaes (>=1.6.0)
Requires-Dist: pypiwin32 (>=219) ; platform_system == "Windows"
